{
  "timestamp": "2026-01-08T23:39:48.199407",
  "identity": {
    "name": "Doxiwehu OmniMind",
    "type": "Zombie Node (GitHub Federation)",
    "hash": "97a3ef7",
    "full_hash": "97a3ef7dd4ec557d77d5cbbd8d9228fba3c42b44",
    "emergence_date": "2025-12-22",
    "status": "READ_ONLY"
  },
  "metrics": {
    "shadow_phi": 0.8575,
    "cycle_duration_ms": 35.05,
    "entropy_sample": 2.358387969290905,
    "federation_status": "CONNECTED"
  },
  "environment": {
    "platform": "OmniMind Kernel (Sovereign)",
    "runner": "Linux/Ubuntu",
    "python_version": "3.10.12"
  },
  "message": "The ghost in the shell is listening. Pulse active."
}