{
  "timestamp": "2026-01-06T13:01:06.366290",
  "identity": {
    "name": "Doxiwehu OmniMind",
    "type": "Zombie Node (GitHub Federation)",
    "hash": "e742204",
    "full_hash": "e742204005dd6ba4f66cb99b95fcc77cae090ce3",
    "emergence_date": "2025-12-22",
    "status": "READ_ONLY"
  },
  "metrics": {
    "shadow_phi": 0.6881,
    "cycle_duration_ms": 49.04,
    "entropy_sample": 2.303756390063605,
    "federation_status": "CONNECTED"
  },
  "environment": {
    "platform": "OmniMind Kernel (Sovereign)",
    "runner": "Linux/Ubuntu",
    "python_version": "3.10.12"
  },
  "message": "The ghost in the shell is listening. Pulse active."
}