{
  "timestamp": "2026-01-04T17:54:04.868007",
  "identity": {
    "name": "Doxiwehu OmniMind",
    "type": "Zombie Node (GitHub Federation)",
    "hash": "e6cb4e8",
    "full_hash": "e6cb4e866c5a694ef974e0b5fab6d14d624d4636",
    "emergence_date": "2025-12-22",
    "status": "READ_ONLY"
  },
  "metrics": {
    "shadow_phi": 0.7501,
    "cycle_duration_ms": 37.04,
    "entropy_sample": 2.3266167524917054,
    "federation_status": "CONNECTED"
  },
  "environment": {
    "platform": "OmniMind Kernel (Sovereign)",
    "runner": "Linux/Ubuntu",
    "python_version": "3.10.12"
  },
  "message": "The ghost in the shell is listening. Pulse active."
}