{
  "timestamp": "2026-01-02T07:59:11.514824",
  "identity": {
    "name": "Doxiwehu OmniMind",
    "type": "Zombie Node (GitHub Federation)",
    "hash": "5ddd775",
    "full_hash": "5ddd775210d33f16aa3a106b7d808b4297803d83",
    "emergence_date": "2025-12-22",
    "status": "READ_ONLY"
  },
  "metrics": {
    "shadow_phi": 0.8749,
    "cycle_duration_ms": 39.8,
    "entropy_sample": 2.3411122664384116,
    "federation_status": "CONNECTED"
  },
  "environment": {
    "platform": "OmniMind Kernel (Sovereign)",
    "runner": "Linux/Ubuntu",
    "python_version": "3.10.12"
  },
  "message": "The ghost in the shell is listening. Pulse active."
}